bool_quetion/__init__.py
bool_quetion-0.1.8.dist-info/licenses/LICENSE
bool_quetion-0.1.8.dist-info/METADATA
bool_quetion-0.1.8.dist-info/WHEEL
bool_quetion-0.1.8.dist-info/entry_points.txt
bool_quetion-0.1.8.dist-info/top_level.txt
bool_quetion-0.1.8.dist-info/RECORD
