Metadata-Version: 2.4
Name: bool_quetion
Version: 0.1.8
Summary: Python-module for asking yes/no or accept/cancel questions
Author-email: Pablo Alejandro Carravetti <gpablinux@gmail.com>
License: GNU General Public License v3.0
Project-URL: Homepage, https://github.com/pablinet/bool_quetion
License-File: LICENSE
Requires-Dist: localized_message
Dynamic: license-file
